FuXLogger/__init__.py
FuXLogger/__metadata__.py
FuXLogger/defaultLogger.py
FuXLogger/exceptions.py
FuXLogger/core/LogBody.py
FuXLogger/core/LogManager.py
FuXLogger/core/__init__.py
FuXLogger/core/formatter.py
FuXLogger/core/handlers.py
FuXLogger/core/logcolor.py
FuXLogger/core/logger.py
FuXLogger/core/loglevel.py
FuXLogger/core/handlers/__init__.py
FuXLogger/core/handlers/file_handler.py
FuXLogger/core/handlers/handler_base.py
FuXLogger/core/handlers/network_handler.py
FuXLogger/core/handlers/stream_handler.py
FuXLogger/extension/__init__.py
FuXLogger/models/__init__.py
FuXLogger/models/log_body.py
FuXLogger/models/log_level.py
FuXLogger/utils/LogQueue.py
FuXLogger/utils/__init__.py
FuXLogger/utils/_typeInfo.py
FuXLogger/utils/color.py
FuXLogger/utils/decorators.py
FuXLogger/utils/exceptions.py
FuXLogger/utils/excformat.py
FuXLogger/utils/exechook.py
FuXLogger/utils/helpers.py
FuXLogger/utils/interfaces.py
FuXLogger/utils/log_queue.py
FuXLogger/utils/obj_builder.py
FuXLogger/utils/timeutil.py
FuXLogger/utils/type_hints.py
FuXLogger/utils/types.py
FuXLogger-0.2.7.post4.dist-info/LICENSE
FuXLogger-0.2.7.post4.dist-info/METADATA
FuXLogger-0.2.7.post4.dist-info/WHEEL
FuXLogger-0.2.7.post4.dist-info/top_level.txt
FuXLogger-0.2.7.post4.dist-info/RECORD
