Metadata-Version: 2.1
Name: FuXLogger
Version: 0.2.7.post4
Summary: A useful logging library for Python
Home-page: https://github.com/Fuxuan-CN/FuXLogger
Author: <符玄(Fuxuan-CN)>
Author-email: 3072252442@qq.com
License: CC-BY-NC-SA 4.0
Classifier: Programming Language :: Python :: 3
Classifier: License :: OSI Approved :: MIT License
Classifier: Operating System :: OS Independent
License-File: LICENSE
